Classfile /d:/Studying/4.1/Compile/lr2/Compiler_repo/rust_compiler/compiler/helperJavaProject/out/production/ModuleTest/AbstractTransport.class
  Last modified 14 ���. 2024 �.; size 365 bytes
  SHA-256 checksum 99dbc13bc477e2654bf0c94091899920823f72a965ff7e633c4ccc7c238cb8f4
  Compiled from "AbstractTransport.java"
public abstract class AbstractTransport
  minor version: 0
  major version: 61
  flags: (0x0421) ACC_PUBLIC, ACC_SUPER, ACC_ABSTRACT
  this_class: #7                          // AbstractTransport
  super_class: #2                         // java/lang/Object
  interfaces: 0, fields: 0, methods: 3, attributes: 1
Constant pool:
   #1 = Methodref          #2.#3          // java/lang/Object."<init>":()V
   #2 = Class              #4             // java/lang/Object
   #3 = NameAndType        #5:#6          // "<init>":()V
   #4 = Utf8               java/lang/Object
   #5 = Utf8               <init>
   #6 = Utf8               ()V
   #7 = Class              #8             // AbstractTransport
   #8 = Utf8               AbstractTransport
   #9 = Utf8               Code
  #10 = Utf8               LineNumberTable
  #11 = Utf8               LocalVariableTable
  #12 = Utf8               this
  #13 = Utf8               LAbstractTransport;
  #14 = Utf8               kmph
  #15 = Utf8               canRide
  #16 = Utf8               ()Z
  #17 = Utf8               SourceFile
  #18 = Utf8               AbstractTransport.java
{
  public AbstractTransport();
    descriptor: ()V
    flags: (0x0001) ACC_PUBLIC
    Code:
      stack=1, locals=1, args_size=1
         0: aload_0
         1: invokespecial #1                  // Method java/lang/Object."<init>":()V
         4: return
      LineNumberTable:
        line 1: 0
      LocalVariableTable:
        Start  Length  Slot  Name   Signature
            0       5     0  this   LAbstractTransport;

  public abstract void kmph();
    descriptor: ()V
    flags: (0x0401) ACC_PUBLIC, ACC_ABSTRACT

  public boolean canRide();
    descriptor: ()Z
    flags: (0x0001) ACC_PUBLIC
    Code:
      stack=1, locals=1, args_size=1
         0: iconst_1
         1: ireturn
      LineNumberTable:
        line 5: 0
      LocalVariableTable:
        Start  Length  Slot  Name   Signature
            0       2     0  this   LAbstractTransport;
}
SourceFile: "AbstractTransport.java"
