public class Main {
    public static void main(String[] args) {
        int arr[] = {1, 2, 3, 4, 5};
        for (int a : arr) {
            System.out.println(a);
        }

Classfile /d:/Studying/4.1/Compile/lr2/Compiler_repo/rust_compiler/compiler/helperJavaProject/out/production/ModuleTest/Main.class
  Last modified 17 ���. 2024 �.; size 633 bytes
  SHA-256 checksum e4fc84c14e5f1a3d25b4d65658d8daaa8ac1352ace1ed25986e62ee309c3f104
  Compiled from "Main.java"
public class Main
  minor version: 0
  major version: 61
  flags: (0x0021) ACC_PUBLIC, ACC_SUPER
  this_class: #19                         // Main
  super_class: #2                         // java/lang/Object
  interfaces: 0, fields: 0, methods: 2, attributes: 1
Constant pool:
   #1 = Methodref          #2.#3          // java/lang/Object."<init>":()V
   #2 = Class              #4             // java/lang/Object
   #3 = NameAndType        #5:#6          // "<init>":()V
   #4 = Utf8               java/lang/Object
   #5 = Utf8               <init>
   #6 = Utf8               ()V
   #7 = Fieldref           #8.#9          // java/lang/System.out:Ljava/io/PrintStream;
   #8 = Class              #10            // java/lang/System
   #9 = NameAndType        #11:#12        // out:Ljava/io/PrintStream;
  #10 = Utf8               java/lang/System
  #11 = Utf8               out
  #12 = Utf8               Ljava/io/PrintStream;
  #13 = Methodref          #14.#15        // java/io/PrintStream.println:(I)V
  #14 = Class              #16            // java/io/PrintStream
  #15 = NameAndType        #17:#18        // println:(I)V
  #16 = Utf8               java/io/PrintStream
  #17 = Utf8               println
  #18 = Utf8               (I)V
  #19 = Class              #20            // Main
  #20 = Utf8               Main
  #21 = Utf8               Code
  #22 = Utf8               LineNumberTable
  #23 = Utf8               LocalVariableTable
  #24 = Utf8               this
  #25 = Utf8               LMain;
  #26 = Utf8               main
  #27 = Utf8               ([Ljava/lang/String;)V
  #28 = Utf8               a
  #29 = Utf8               I
  #30 = Utf8               args
  #31 = Utf8               [Ljava/lang/String;
  #32 = Utf8               arr
  #33 = Utf8               [I
  #34 = Utf8               StackMapTable
  #35 = Class              #31            // "[Ljava/lang/String;"
  #36 = Class              #33            // "[I"
  #37 = Utf8               SourceFile
  #38 = Utf8               Main.java
{
  public Main();
    descriptor: ()V
    flags: (0x0001) ACC_PUBLIC
    Code:
      stack=1, locals=1, args_size=1
         0: aload_0
         1: invokespecial #1                  // Method java/lang/Object."<init>":()V
         4: return
      LineNumberTable:
        line 3: 0
      LocalVariableTable:
        Start  Length  Slot  Name   Signature
            0       5     0  this   LMain;

  public static void main(java.lang.String[]);
    descriptor: ([Ljava/lang/String;)V
    flags: (0x0009) ACC_PUBLIC, ACC_STATIC
    Code:
      stack=4, locals=6, args_size=1
         0: iconst_5
         1: newarray       int
         3: dup
         4: iconst_0
         5: iconst_1
         6: iastore
         7: dup
         8: iconst_1
         9: iconst_2
        10: iastore
        11: dup
        12: iconst_2
        13: iconst_3
        14: iastore
        15: dup
        16: iconst_3
        17: iconst_4
        18: iastore
        19: dup
        20: iconst_4
        21: iconst_5
        22: iastore
        23: astore_1
        24: aload_1
        25: astore_2
        26: aload_2
        27: arraylength
        28: istore_3
        29: iconst_0
        30: istore        4
        32: iload         4
        34: iload_3
        35: if_icmpge     58
        38: aload_2
        39: iload         4
        41: iaload
        42: istore        5
        44: getstatic     #7                  // Field java/lang/System.out:Ljava/io/PrintStream;
        47: iload         5
        49: invokevirtual #13                 // Method java/io/PrintStream.println:(I)V
        52: iinc          4, 1
        55: goto          32
        58: return
      LineNumberTable:
        line 5: 0
        line 6: 24
        line 7: 44
        line 6: 52
        line 90: 58
      LocalVariableTable:
        Start  Length  Slot  Name   Signature
           44       8     5     a   I
            0      59     0  args   [Ljava/lang/String;
           24      35     1   arr   [I
      StackMapTable: number_of_entries = 2
        frame_type = 255 /* full_frame */
          offset_delta = 32
          locals = [ class "[Ljava/lang/String;", class "[I", class "[I", int, int ]
          stack = []
        frame_type = 248 /* chop */
          offset_delta = 25
}
SourceFile: "Main.java"
