public class Main {
    public static void main(String[] args) {
          Car x = new Bus();
          x.speedup(); //родительский
          x.speed(); // свой переопределенный
          Car.ride(); // статик родителя
          Bus.ride(); // статик свой

Classfile /d:/Studying/4.1/Compile/lr2/Compiler_repo/rust_compiler/compiler/helperJavaProject/out/production/ModuleTest/Main.class
  Last modified 20 ���. 2024 �.; size 502 bytes
  SHA-256 checksum 47eb95bbaa136ce69cee5ef664104916f82f34950ee378dee593043042cdfb32
  Compiled from "Main.java"
public class Main
  minor version: 0
  major version: 61
  flags: (0x0021) ACC_PUBLIC, ACC_SUPER
  this_class: #22                         // Main
  super_class: #2                         // java/lang/Object
  interfaces: 0, fields: 0, methods: 2, attributes: 1
Constant pool:
   #1 = Methodref          #2.#3          // java/lang/Object."<init>":()V
   #2 = Class              #4             // java/lang/Object
   #3 = NameAndType        #5:#6          // "<init>":()V
   #4 = Utf8               java/lang/Object
   #5 = Utf8               <init>
   #6 = Utf8               ()V
   #7 = Class              #8             // Bus
   #8 = Utf8               Bus
   #9 = Methodref          #7.#3          // Bus."<init>":()V
  #10 = Methodref          #11.#12        // Car.speedup:()V
  #11 = Class              #13            // Car
  #12 = NameAndType        #14:#6         // speedup:()V
  #13 = Utf8               Car
  #14 = Utf8               speedup
  #15 = Methodref          #11.#16        // Car.speed:()V
  #16 = NameAndType        #17:#6         // speed:()V
  #17 = Utf8               speed
  #18 = Methodref          #11.#19        // Car.ride:()V
  #19 = NameAndType        #20:#6         // ride:()V
  #20 = Utf8               ride
  #21 = Methodref          #7.#19         // Bus.ride:()V
  #22 = Class              #23            // Main
  #23 = Utf8               Main
  #24 = Utf8               Code
  #25 = Utf8               LineNumberTable
  #26 = Utf8               LocalVariableTable
  #27 = Utf8               this
  #28 = Utf8               LMain;
  #29 = Utf8               main
  #30 = Utf8               ([Ljava/lang/String;)V
  #31 = Utf8               args
  #32 = Utf8               [Ljava/lang/String;
  #33 = Utf8               x
  #34 = Utf8               LCar;
  #35 = Utf8               SourceFile
  #36 = Utf8               Main.java
{
  public Main();
    descriptor: ()V
    flags: (0x0001) ACC_PUBLIC
    Code:
      stack=1, locals=1, args_size=1
         0: aload_0
         1: invokespecial #1                  // Method java/lang/Object."<init>":()V
         4: return
      LineNumberTable:
        line 3: 0
      LocalVariableTable:
        Start  Length  Slot  Name   Signature
            0       5     0  this   LMain;

  public static void main(java.lang.String[]);
    descriptor: ([Ljava/lang/String;)V
    flags: (0x0009) ACC_PUBLIC, ACC_STATIC
    Code:
      stack=2, locals=2, args_size=1
         0: new           #7                  // class Bus
         3: dup
         4: invokespecial #9                  // Method Bus."<init>":()V
         7: astore_1
         8: aload_1
         9: invokevirtual #10                 // Method Car.speedup:()V
        12: aload_1
        13: invokevirtual #15                 // Method Car.speed:()V
        16: invokestatic  #18                 // Method Car.ride:()V
        19: invokestatic  #21                 // Method Bus.ride:()V
        22: return
      LineNumberTable:
        line 5: 0
        line 6: 8
        line 7: 12
        line 8: 16
        line 9: 19
        line 97: 22
      LocalVariableTable:
        Start  Length  Slot  Name   Signature
            0      23     0  args   [Ljava/lang/String;
            8      15     1     x   LCar;
}
SourceFile: "Main.java"
