Classfile /d:/Studying/4.1/Compile/lr2/Compiler_repo/rust_compiler/compiler/helperJavaProject/out/production/ModuleTest/Main.class
  Last modified 14 ���. 2024 �.; size 599 bytes
  SHA-256 checksum c44f2f638dc00f6c3a663a2210f48a37e5f27487bc0df960f5852f15569c9f56
  Compiled from "Main.java"
public class Main
  minor version: 0
  major version: 61
  flags: (0x0021) ACC_PUBLIC, ACC_SUPER
  this_class: #23                         // Main
  super_class: #2                         // java/lang/Object
  interfaces: 0, fields: 0, methods: 2, attributes: 1
Constant pool:
   #1 = Methodref          #2.#3          // java/lang/Object."<init>":()V
   #2 = Class              #4             // java/lang/Object
   #3 = NameAndType        #5:#6          // "<init>":()V
   #4 = Utf8               java/lang/Object
   #5 = Utf8               <init>
   #6 = Utf8               ()V
   #7 = Double             1.0E12d
   #9 = Fieldref           #10.#11        // java/lang/System.out:Ljava/io/PrintStream;
  #10 = Class              #12            // java/lang/System
  #11 = NameAndType        #13:#14        // out:Ljava/io/PrintStream;
  #12 = Utf8               java/lang/System
  #13 = Utf8               out
  #14 = Utf8               Ljava/io/PrintStream;
  #15 = String             #16            // Message
  #16 = Utf8               Message
  #17 = Methodref          #18.#19        // java/io/PrintStream.print:(Ljava/lang/String;)V
  #18 = Class              #20            // java/io/PrintStream
  #19 = NameAndType        #21:#22        // print:(Ljava/lang/String;)V
  #20 = Utf8               java/io/PrintStream
  #21 = Utf8               print
  #22 = Utf8               (Ljava/lang/String;)V
  #23 = Class              #24            // Main
  #24 = Utf8               Main
  #25 = Utf8               Code
  #26 = Utf8               LineNumberTable
  #27 = Utf8               LocalVariableTable
  #28 = Utf8               this
  #29 = Utf8               LMain;
  #30 = Utf8               main
  #31 = Utf8               ([Ljava/lang/String;)V
  #32 = Utf8               args
  #33 = Utf8               [Ljava/lang/String;
  #34 = Utf8               z
  #35 = Utf8               I
  #36 = Utf8               d1
  #37 = Utf8               D
  #38 = Utf8               x1
  #39 = Utf8               C
  #40 = Utf8               SourceFile
  #41 = Utf8               Main.java
{
  public Main();
    descriptor: ()V
    flags: (0x0001) ACC_PUBLIC
    Code:
      stack=1, locals=1, args_size=1
         0: aload_0
         1: invokespecial #1                  // Method java/lang/Object."<init>":()V
         4: return
      LineNumberTable:
        line 3: 0
      LocalVariableTable:
        Start  Length  Slot  Name   Signature
            0       5     0  this   LMain;

  public static void main(java.lang.String[]);
    descriptor: ([Ljava/lang/String;)V
    flags: (0x0009) ACC_PUBLIC, ACC_STATIC
    Code:
      stack=2, locals=28, args_size=1
         0: bipush        10
         2: istore        24
         4: ldc2_w        #7                  // double 1.0E12d
         7: dstore        25
         9: bipush        99
        11: istore        27
        13: getstatic     #9                  // Field java/lang/System.out:Ljava/io/PrintStream;
        16: ldc           #15                 // String Message
        18: invokevirtual #17                 // Method java/io/PrintStream.print:(Ljava/lang/String;)V
        21: return
      LineNumberTable:
        line 6: 0
        line 7: 4
        line 8: 9
        line 9: 13
        line 31: 21
      LocalVariableTable:
        Start  Length  Slot  Name   Signature
            0      22     0  args   [Ljava/lang/String;
            4      18    24     z   I
            9      13    25    d1   D
           13       9    27    x1   C
}
SourceFile: "Main.java"
