Classfile /c:/Users/arsen/Desktop/ModuleTest/out/production/ModuleTest/Main.class
  Last modified 13 ���. 2024 �.; size 1340 bytes
  SHA-256 checksum a25a34f4660e81d806f20bedca9ace981941611106c39dc4fe62e23e566eb6f0
  Compiled from "Main.java"
public class Main
  minor version: 0
  major version: 61
  flags: (0x0021) ACC_PUBLIC, ACC_SUPER
  this_class: #32                         // Main
  super_class: #2                         // java/lang/Object
  interfaces: 0, fields: 0, methods: 2, attributes: 3
Constant pool:
   #1 = Methodref          #2.#3          // java/lang/Object."<init>":()V
   #2 = Class              #4             // java/lang/Object
   #3 = NameAndType        #5:#6          // "<init>":()V
   #4 = Utf8               java/lang/Object
   #5 = Utf8               <init>
   #6 = Utf8               ()V
   #7 = Class              #8             // One
   #8 = Utf8               One
   #9 = Methodref          #7.#3          // One."<init>":()V
  #10 = Class              #11            // dir/Two
  #11 = Utf8               dir/Two
  #12 = Methodref          #10.#3         // dir/Two."<init>":()V
  #13 = Class              #14            // dir/Three
  #14 = Utf8               dir/Three
  #15 = Methodref          #13.#3         // dir/Three."<init>":()V
  #16 = Fieldref           #17.#18        // java/lang/System.out:Ljava/io/PrintStream;
  #17 = Class              #19            // java/lang/System
  #18 = NameAndType        #20:#21        // out:Ljava/io/PrintStream;
  #19 = Utf8               java/lang/System
  #20 = Utf8               out
  #21 = Utf8               Ljava/io/PrintStream;
  #22 = InvokeDynamic      #0:#23         // #0:makeConcatWithConstants:(II)Ljava/lang/String;
  #23 = NameAndType        #24:#25        // makeConcatWithConstants:(II)Ljava/lang/String;
  #24 = Utf8               makeConcatWithConstants
  #25 = Utf8               (II)Ljava/lang/String;
  #26 = Methodref          #27.#28        // java/io/PrintStream.println:(Ljava/lang/String;)V
  #27 = Class              #29            // java/io/PrintStream
  #28 = NameAndType        #30:#31        // println:(Ljava/lang/String;)V
  #29 = Utf8               java/io/PrintStream
  #30 = Utf8               println
  #31 = Utf8               (Ljava/lang/String;)V
  #32 = Class              #33            // Main
  #33 = Utf8               Main
  #34 = Utf8               Code
  #35 = Utf8               LineNumberTable
  #36 = Utf8               LocalVariableTable
  #37 = Utf8               this
  #38 = Utf8               LMain;
  #39 = Utf8               main
  #40 = Utf8               ([Ljava/lang/String;)V
  #41 = Utf8               i
  #42 = Utf8               I
  #43 = Utf8               args
  #44 = Utf8               [Ljava/lang/String;
  #45 = Utf8               o1
  #46 = Utf8               LOne;
  #47 = Utf8               t2
  #48 = Utf8               Ldir/Two;
  #49 = Utf8               t3
  #50 = Utf8               Ldir/Three;
  #51 = Utf8               j
  #52 = Utf8               k
  #53 = Utf8               StackMapTable
  #54 = Class              #44            // "[Ljava/lang/String;"
  #55 = Utf8               SourceFile
  #56 = Utf8               Main.java
  #57 = Utf8               BootstrapMethods
  #58 = MethodHandle       6:#59          // REF_invokeStatic java/lang/invoke/StringConcatFactory.makeConcatWithConstants:(Ljava/lang/invoke/MethodHandles$Lookup;Ljava/lang/String;Ljava/lang/invoke/MethodType;Ljava/lang/String;[Ljava/lang/Object;)Ljava/lang/invoke/CallSite;
  #59 = Methodref          #60.#61        // java/lang/invoke/StringConcatFactory.makeConcatWithConstants:(Ljava/lang/invoke/MethodHandles$Lookup;Ljava/lang/String;Ljava/lang/invoke/MethodType;Ljava/lang/String;[Ljava/lang/Object;)Ljava/lang/invoke/CallSite;
  #60 = Class              #62            // java/lang/invoke/StringConcatFactory
  #61 = NameAndType        #24:#63        // makeConcatWithConstants:(Ljava/lang/invoke/MethodHandles$Lookup;Ljava/lang/String;Ljava/lang/invoke/MethodType;Ljava/lang/String;[Ljava/lang/Object;)Ljava/lang/invoke/CallSite;
  #62 = Utf8               java/lang/invoke/StringConcatFactory
  #63 = Utf8               (Ljava/lang/invoke/MethodHandles$Lookup;Ljava/lang/String;Ljava/lang/invoke/MethodType;Ljava/lang/String;[Ljava/lang/Object;)Ljava/lang/invoke/CallSite;
  #64 = String             #65            // \u0001 \u0001
  #65 = Utf8               \u0001 \u0001
  #66 = Utf8               InnerClasses
  #67 = Class              #68            // java/lang/invoke/MethodHandles$Lookup
  #68 = Utf8               java/lang/invoke/MethodHandles$Lookup
  #69 = Class              #70            // java/lang/invoke/MethodHandles
  #70 = Utf8               java/lang/invoke/MethodHandles
  #71 = Utf8               Lookup
{
  public Main();
    descriptor: ()V
    flags: (0x0001) ACC_PUBLIC
    Code:
      stack=1, locals=1, args_size=1
         0: aload_0
         1: invokespecial #1                  // Method java/lang/Object."<init>":()V
         4: return
      LineNumberTable:
        line 3: 0
      LocalVariableTable:
        Start  Length  Slot  Name   Signature
            0       5     0  this   LMain;

  public static void main(java.lang.String[]);
    descriptor: ([Ljava/lang/String;)V
    flags: (0x0009) ACC_PUBLIC, ACC_STATIC
    Code:
      stack=3, locals=7, args_size=1
         0: new           #7                  // class One
         3: dup
         4: invokespecial #9                  // Method One."<init>":()V
         7: astore_1
         8: new           #10                 // class dir/Two
        11: dup
        12: invokespecial #12                 // Method dir/Two."<init>":()V
        15: astore_2
        16: new           #13                 // class dir/Three
        19: dup
        20: invokespecial #15                 // Method dir/Three."<init>":()V
        23: astore_3
        24: iconst_0
        25: istore        4
        27: iconst_0
        28: istore        5
        30: iload         5
        32: iconst_4
        33: if_icmpge     58
        36: iload         5
        38: iconst_2
        39: if_icmpne     45
        42: goto          58
        45: iload         4
        47: iload         5
        49: iadd
        50: istore        4
        52: iinc          5, 1
        55: goto          30
        58: iconst_0
        59: istore        5
        61: iconst_0
        62: istore        6
        64: iload         6
        66: iconst_4
        67: if_icmpge     93
        70: iload         6
        72: iconst_2
        73: irem
        74: ifne          80
        77: goto          87
        80: iload         5
        82: iload         6
        84: iadd
        85: istore        5
        87: iinc          6, 1
        90: goto          64
        93: getstatic     #16                 // Field java/lang/System.out:Ljava/io/PrintStream;
        96: iload         4
        98: iload         5
       100: invokedynamic #22,  0             // InvokeDynamic #0:makeConcatWithConstants:(II)Ljava/lang/String;
       105: invokevirtual #26                 // Method java/io/PrintStream.println:(Ljava/lang/String;)V
       108: return
      LineNumberTable:
        line 5: 0
        line 6: 8
        line 7: 16
        line 9: 24
        line 10: 27
        line 11: 36
        line 12: 42
        line 14: 45
        line 10: 52
        line 17: 58
        line 18: 61
        line 19: 70
        line 20: 77
        line 22: 80
        line 18: 87
        line 25: 93
        line 26: 108
      LocalVariableTable:
        Start  Length  Slot  Name   Signature
           30      28     5     i   I
           64      29     6     i   I
            0     109     0  args   [Ljava/lang/String;
            8     101     1    o1   LOne;
           16      93     2    t2   Ldir/Two;
           24      85     3    t3   Ldir/Three;
           27      82     4     j   I
           61      48     5     k   I
      StackMapTable: number_of_entries = 7
        frame_type = 255 /* full_frame */
          offset_delta = 30
          locals = [ class "[Ljava/lang/String;", class One, class dir/Two, class dir/Three, int, int ]
          stack = []
        frame_type = 14 /* same */
        frame_type = 250 /* chop */
          offset_delta = 12
        frame_type = 253 /* append */
          offset_delta = 5
          locals = [ int, int ]
        frame_type = 15 /* same */
        frame_type = 6 /* same */
        frame_type = 250 /* chop */
          offset_delta = 5
}
SourceFile: "Main.java"
BootstrapMethods:
  0: #58 REF_invokeStatic java/lang/invoke/StringConcatFactory.makeConcatWithConstants:(Ljava/lang/invoke/MethodHandles$Lookup;Ljava/lang/String;Ljava/lang/invoke/MethodType;Ljava/lang/String;[Ljava/lang/Object;)Ljava/lang/invoke/CallSite;
    Method arguments:
      #64 \u0001 \u0001
InnerClasses:
  public static final #71= #67 of #69;    // Lookup=class java/lang/invoke/MethodHandles$Lookup of class java/lang/invoke/MethodHandles
